pytest_pt.py
pytest_pt-1.0.0.dist-info/LICENSE
pytest_pt-1.0.0.dist-info/METADATA
pytest_pt-1.0.0.dist-info/WHEEL
pytest_pt-1.0.0.dist-info/top_level.txt
pytest_pt-1.0.0.dist-info/RECORD
