Metadata-Version: 2.1
Name: pytest-pt
Version: 1.0.0
Summary: pytest plugin to use *.pt files as tests
Author-email: "Curt J. Sampson" <cjs@cynic.net>
License: All code in this repo is released under CC0.
Project-URL: homepage, https://github.com/cynic-net/pytest-pt
Project-URL: source, https://github.com/cynic-net/pytest-pt
Project-URL: tracker, https://github.com/cynic-net/pytest-pt/issues
Classifier: Development Status :: 5 - Production/Stable
Classifier: Intended Audience :: Developers
Classifier: Framework :: Pytest
Classifier: Topic :: Software Development :: Testing
Classifier: Programming Language :: Python :: 3 :: Only
Classifier: License :: CC0 1.0 Universal (CC0 1.0) Public Domain Dedication
Requires-Python: >=3.6
License-File: LICENSE
Requires-Dist: pytest
